{
	"_type":"world",
	"serverInfo":{
					"master":true,
					"id":0,
					"mongoHost":"",
					"mongoPort":"",
					"mongoUser":"",
					"mongoPasswd":""
	},
	"universeInfo":{
					"procTimePerEpoch": 0.0,
	                "numStars":200,
	                "universeDims":[10.0, 10.0, 10.0],
	                "solarSystemDims":{"min":5.0, "max":30.0},
	                "avgPlanets":5,
	                "starEnergyOpts":{"min":1000.0, "max":100000.0},
	                "starRadiusOpts":{"min":0.0046, "max":0.046},
	                "planetEnergyOpts":{"min":0.0, "max":1000.0},
	                "planetRawMatOpts":{"min":0.0, "max":1000.0},
	                "planetRadiusOpts":{"min":0.000004, "max":0.0004},
	                "timeStep": 0.1,
	                "epoch":1,
	                "runTime": 0.0,
	                "numClans":1,
	                "clanNames":[1,2,3,4,5,6,7,8,9],
	                "clanConsumeRates":0.1,
	                "agentTypes":{"explorer":0, "harvestor":1, "trader":2, "soldier":3},
	                "maxPopn": 100,
	                "initPopn": 90,
	                "maxAge": 500,
	                "minAgeReprod":50,
	                "maxAgeReprod": 300,
	                "multiChildren":false,
	                "agentTypeMix":[100.0, 0.0, 0.0, 0.0],
	                "starCoords":[],
	                "popnOverTime":[],
	                "generationFitness":{}
	},
	"universeInfoDesc":{
				"procTimePerEpoch": "Actual seconds per epoch",
                "numStars":"Total Stars",
                "universeDims":"Size of the universe (light-years)",
                "solarSystemDims":"Average Solar system dimension - LY",
                "avgPlanets":"Average planets per solar system",
                "starEnergyOpts":"Energy amounts possible on a star - MegaWatts?",
                "starRadiusOpts":"Star Radius Options",
                "planetEnergyOpts":"Energy amounts possible on a planet - MegaWatts?",
                "planetRawMatOpts":"Raw Material amounts possible on a planet - Tons?",
                "planetRadiusOpts":"Planet Sizes LY",
                "timeStep": "Timestep - seconds",
                "epoch":"Epoch starts at 1 so we instantiate systems at epoch 0, and can start processing",
                "runTime": "Time elapsed since start",
                "numClans":"Number of Clans",
                "clanConsumeRates":"Clan consumption rates",
                "agentTypes":"names and index numbers for agent arrays",
                "maxPopn": "Max Population - initially",
                "maxAge": "Max Age (epochs) - after which chances of dying mount exponentially",
                "initPopn": "Initiisation population level",
                "minAgeReprod":"Reprod min age",
                "maxAgeReprod": "Reprod max age",
                "agentTypeMix":"Mix of types [ex, fa, ha, tr] (percentages of total popn)",
                "starCoords":"Coordinates of star systems",
                "popnOverTime":"Store for population over time",
                "generationFitness":""
	},
	"gaInfo":{
				"crossoverTraits":["vis", "velMag", "offence", "defence"],
				"mutationBounds":{"min":-0.05, "max":0.05},
				"fitnessReqs":{
					"0":{
									"vis":{"val":3.0, "operator":"gte", "units":"au"},
									"velMag":{"val":4.0, "operator":"gte", "units":"au"},
									"offence":{"val":0.0, "operator":"gte", "units":"conflict"},
									"defence":{"val":0.1, "operator":"gte", "units":"conflict"}
								},
					"1":{
									"vis":{"val":0.0, "operator":"gte", "units":"au"},
									"velMag":{"val":7.0, "operator":"gte", "units":"au"},
									"offence":{"val":0.0, "operator":"gte", "units":"conflict"},
									"defence":{"val":3.0, "operator":"gte", "units":"conflict"}
								},
					"2":{
									"vis":{"val":0.0, "operator":"gte", "units":"au"},
									"velMag":{"val":4.0, "operator":"gte", "units":"au"},
									"offence":{"val":0.0, "operator":"gte", "units":"conflict"},
									"defence":{"val":3.0, "operator":"gte", "units":"conflict"}
								},
					"3":{
									"vis":{"val":3.0, "operator":"gte", "units":"au"},
									"velMag":{"val":7.0, "operator":"gte", "units":"au"},
									"offence":{"val":3.0, "operator":"gte", "units":"conflict"},
									"defence":{"val":3.0, "operator":"gte", "units":"conflict"}
								}
				}
	},
	"celestialInfo":{
		"starInfo":{
						"_type":"star",
		               "position":[],
		               "radius":0.0,
		               "typeId":0,
		               "energyStore": 0,
		               "epoch":0,
		               "status":"waiting"
		            },
		 "planetInfo":{
						"_type":"planet",
		                 "starId":0,
		                 "position":[],
		                 "radius":0.0,
		                 "typeId":0,
		                 "energyStore":0.0,
		                 "rawMatStore":0.0
		            }
	},
	"clanInfo":{
				"_type":"clan",
				"clanName":"",
	            "starId":0,
	            "position":[],
	            "planetId":0,
	            "energyConsumeRate":0.0,
	            "resourceKnowledge":[],
	            "starCatalogue":[],
				"consumption":{
					"energy":1.0,
					"rawMat":1.0
				},
				"techLevel":{
					"explorer":1,
					"harvestor":1,
					"trader":1,
					"soldier":1
				}
	},
	"agentInfo":{
		"traitDesc":{
					         "agentType":"Type of agent",
					         "clanId":"Mongo Doc ID of clan",
					         "vis":"Range of visibility",
					         "reprodChance":"Chance of reproduction",
					         "socialLinkAgeRate":"Rate at which the agents social network ages",
					         "velMag":"Velocity magnitude - in LY - everything is in LY",
					         "parent":"Whether the agent has already reproduced",
					         "actyGroup":"Current agent activity group",
					         "actyData":"Activity data",
		                     "actyId":"Current acty within the group",
		                     "actyIdx":"Index of this acty in the group",
					         "destination":"Where the agent is heading to",
					         "position":"3D position",
					         "velocity":"3D velocity unit",
					         "starId":"star system agent currently resides in",
					         "epoch":"Current processing epoch",
					         "messages":"Inter-agent messages",
					         "generation":"Generation number"
		},
		"explorer":{
							"_type":"agent",
							"agentType":0,
							"clanId":0,
							"vis":0.0,
							"reprodChance":0.0,
							"socialLinkAgeRate":0.0,
							"velMag":0.0,
							"defence":0.0,
							"offence":0.0,
							"canReproduce":false,
							"reproduceOpts":[],
							"generation":0,
							"parent":false,
							"childOf":[],
							"actyGroup":0,
							"actyData":{"complete":false,
							            "actyId":0,
							            "actyIdx":0,
							            "tgtSys":"",
							            "tgtStarCoords":"",
							            "tgtCoords":""
							            },
							"destination":[],
							"position":[0.0, 0.0, 0.0],
							"velocity":[0.0, 0.0, 0.0],
							"starId":0,
							"epoch":0,
							"messages":[],
							"generation":0,
							"visBounds":{"min":1.0, "max":5.0},
							"velMagBounds":{"min":0.5, "max":1.0},
							"offenceBounds":{"min":0.01, "max":1.0},
							"defenceBounds":{"min":0.01, "max":1.0},
							"rawMatCap":{"min":10.0, "max":100.0},
							"energyCap":{"min":10.0, "max":100.0},
							"explorerGoodCap":{"min":10.0, "max":100.0},
							"rawMatConsume":{"min":0.1, "max":1.0},
							"energyConsume":{"min":0.1, "max":1.0},
							"explorerGoodConsume":{"min":0.001, "max":0.1}
		},
		"harvestor":{
							"_type":"agent",
							"agentType":1,
							"clanId":0,
							"vis":0.0,
							"reprodChance":0.0,
							"socialLinkAgeRate":0.0,
							"velMag":0.0,
							"defence":0.0,
							"offence":0.0,
							"canReproduce":false,
							"reproduceOpts":[],
							"generation":0,
							"parent":false,
							"childOf":[],
							"actyGroup":0,
							"actyData":{"complete":false,
							            "actyId":0,
							            "actyIdx":0},
							"destination":[],
							"position":[0.0, 0.0, 0.0],
							"velocity":[0.0, 0.0, 0.0],
							"starId":0,
							"epoch":0,
							"messages":[],
							"generation":0,
							"visBounds":{"min":0.1, "max":0.25},
							"velMagBounds":{"min":0.05, "max":0.1},
							"offenceBounds":{"min":0.01, "max":1.0},
							"defenceBounds":{"min":0.01, "max":1.0},
							"rawMatCap":{"min":10.0, "max":100.0},
							"energyCap":{"min":10.0, "max":100.0},
							"harvestorGoodCap":{"min":10.0, "max":100.0},
							"rawMatConsume":{"min":0.1, "max":1.0},
							"energyConsume":{"min":0.1, "max":1.0},
							"havestorGoodConsume":{"min":0.001, "max":0.1}
		},
		"trader":{
							"_type":"agent",
							"agentType":2,
							"clanId":0,
							"vis":0.0,
							"reprodChance":0.0,
							"socialLinkAgeRate":0.0,
							"velMag":0.0,
							"defence":0.0,
							"offence":0.0,
							"canReproduce":false,
							"reproduceOpts":[],
							"generation":0,
							"parent":false,
							"childOf":[],
							"actyGroup":0,
							"actyData":{"complete":false,
							            "actyId":0,
							            "actyIdx":0},
							"destination":[],
							"position":[0.0, 0.0, 0.0],
							"velocity":[0.0, 0.0, 0.0],
							"starId":0,
							"epoch":0,
							"messages":[],
							"generation":0,
							"visBounds":{"min":0.1, "max":0.25},
							"velMagBounds":{"min":0.1, "max":0.75},
							"offenceBounds":{"min":0.01, "max":1.0},
							"defenceBounds":{"min":0.01, "max":1.0},
							"rawMatCap":{"min":10.0, "max":100.0},
							"energyCap":{"min":10.0, "max":100.0},
							"traderGoodCap":{"min":10.0, "max":100.0},
							"rawMatConsume":{"min":0.1, "max":1.0},
							"energyConsume":{"min":0.1, "max":1.0},
							"traderGoodConsume":{"min":0.001, "max":0.1}
		},
		"soldier":{
							"_type":"agent",
							"agentType":3,
							"clanId":0,
							"vis":0.0,
							"reprodChance":0.0,
							"socialLinkAgeRate":0.0,
							"velMag":0.0,
							"defence":0.0,
							"offence":0.0,
							"canReproduce":false,
							"reproduceOpts":[],
							"generation":0,
							"parent":false,
							"childOf":[],
							"actyGroup":0,
							"actyData":{"complete":false,
							            "actyId":0,
							            "actyIdx":0},
							"destination":[],
							"position":[0.0, 0.0, 0.0],
							"velocity":[0.0, 0.0, 0.0],
							"starId":0,
							"epoch":0,
							"messages":[],
							"generation":0,
							"visBounds":{"min":1.0, "max":5.0},
							"velMagBounds":{"min":0.01, "max":0.5},
							"offenceBounds":{"min":0.01, "max":1.0},
							"defenceBounds":{"min":0.01, "max":1.0},
							"rawMatCap":{"min":10.0, "max":100.0},
							"energyCap":{"min":10.0, "max":100.0},
							"traderGoodCap":{"min":10.0, "max":100.0},
							"rawMatConsume":{"min":0.1, "max":1.0},
							"energyConsume":{"min":0.1, "max":1.0},
							"traderGoodConsume":{"min":0.001, "max":0.1}
		}
	}
}
